manim_recorder/__init__.py
manim_recorder/__main__.py
manim_recorder/defaults.py
manim_recorder/generate_subcaption.py
manim_recorder/helper.py
manim_recorder/multimedia.py
manim_recorder/service/__init__.py
manim_recorder/service/blank.py
manim_recorder/service/gtts.py
manim_recorder/service/gui_recorder/__init__.py
manim_recorder/service/gui_recorder/__main__.py
manim_recorder/service/gui_recorder/assets/dark_mode/mic.svg
manim_recorder/service/gui_recorder/assets/dark_mode/pause.svg
manim_recorder/service/gui_recorder/assets/dark_mode/play.svg
manim_recorder/service/gui_recorder/assets/dark_mode/stop.svg
manim_recorder/service/gui_recorder/assets/light_mode/mic.svg
manim_recorder/service/gui_recorder/assets/light_mode/pause.svg
manim_recorder/service/gui_recorder/assets/light_mode/play.svg
manim_recorder/service/gui_recorder/assets/light_mode/stop.svg
manim_recorder/service/gui_recorder/config.py
manim_recorder/service/gui_recorder/multimedia.py
manim_recorder/service/gui_recorder/util.py
manim_recorder/sound_effects/__init__.py
manim_recorder/sound_effects/sound/Add.json
manim_recorder/sound_effects/sound/AddTextLetterByLetter.json
manim_recorder/sound_effects/sound/AddTextWordByWord.json
manim_recorder/sound_effects/sound/AnimatedBoundary.json
manim_recorder/sound_effects/sound/Animation.json
manim_recorder/sound_effects/sound/AnimationGroup.json
manim_recorder/sound_effects/sound/ApplyComplexFunction.json
manim_recorder/sound_effects/sound/ApplyMethod.json
manim_recorder/sound_effects/sound/ApplyPointwiseFunction.json
manim_recorder/sound_effects/sound/ApplyPointwiseFunctionToCenter.json
manim_recorder/sound_effects/sound/ApplyWave.json
manim_recorder/sound_effects/sound/Blink.json
manim_recorder/sound_effects/sound/Broadcast.json
manim_recorder/sound_effects/sound/ChangeDecimalToValue.json
manim_recorder/sound_effects/sound/ChangeSpeed.json
manim_recorder/sound_effects/sound/ChangingDecimal.json
manim_recorder/sound_effects/sound/Circumscribe.json
manim_recorder-0.6.0.dist-info/LICENSE
manim_recorder-0.6.0.dist-info/METADATA
manim_recorder-0.6.0.dist-info/WHEEL
manim_recorder-0.6.0.dist-info/entry_points.txt
manim_recorder-0.6.0.dist-info/RECORD
