Metadata-Version: 2.3
Name: manim-recorder
Version: 0.6.0
Summary: Manim plugin for recorder
License: MIT
Keywords: voiceover,manim,recording,math animations
Author: AvN Learn
Author-email: avnlearn@gmail.com
Requires-Python: >=3.9,<=3.13.2
Classifier: Development Status :: 3 - Alpha
Classifier: License :: OSI Approved :: MIT License
Classifier: Programming Language :: Python :: 3
Classifier: Programming Language :: Python :: 3.9
Classifier: Programming Language :: Python :: 3.10
Classifier: Programming Language :: Python :: 3.11
Classifier: Programming Language :: Python :: 3.12
Classifier: Programming Language :: Python :: 3.13
Classifier: Programming Language :: Python :: 3.7
Classifier: Programming Language :: Python :: 3.8
Classifier: Topic :: Multimedia :: Graphics
Classifier: Topic :: Multimedia :: Sound/Audio :: Capture/Recording
Classifier: Topic :: Multimedia :: Sound/Audio :: Speech
Classifier: Topic :: Multimedia :: Video
Classifier: Topic :: Scientific/Engineering
Classifier: Topic :: Scientific/Engineering :: Visualization
Provides-Extra: all
Provides-Extra: blank
Provides-Extra: gtts
Provides-Extra: gui-recorder
Requires-Dist: PyAudio (>=0.2.14,<0.3.0) ; extra == "gui-recorder" or extra == "all"
Requires-Dist: gTTS (>=2.2.4,<3.0.0) ; extra == "gtts" or extra == "all"
Requires-Dist: manim
Requires-Dist: mutagen (>=1.47.0,<2.0.0)
Requires-Dist: pydub (>=0.25.1,<0.26.0)
Requires-Dist: pyqtgraph (>=0.13.7,<0.14.0) ; extra == "gui-recorder"
Requires-Dist: pyside6 (>=6.7.2,<7.0.0) ; extra == "gui-recorder"
Requires-Dist: sox (>=1.5.0,<2.0.0)
